gender_guesser_first_names/__init__.py
gender_guesser_first_names/gender.py
gender_guesser_first_names-0.1.1.dist-info/LICENSE
gender_guesser_first_names-0.1.1.dist-info/METADATA
gender_guesser_first_names-0.1.1.dist-info/WHEEL
gender_guesser_first_names-0.1.1.dist-info/top_level.txt
gender_guesser_first_names-0.1.1.dist-info/RECORD
