Metadata-Version: 2.1
Name: gender_guesser_first_names
Version: 0.1.1
Summary: gender-guesser modified to use first names as input, and allows all the countries
Home-page: https://github.com/colav-playground/gender_guesser_first_names
Author: restrepo
Author-email: restrepo@udea.edu.co
License: BSD
License-File: LICENSE
Requires-Dist: gender-guesser >=0.4.0
